edream_sdk/client/api_client.py
edream_sdk/controllers/dream.py
edream_sdk/controllers/file_upload.py
edream_sdk/controllers/playlist.py
edream_sdk/controllers/user.py
edream_sdk/models/api_types.py
edream_sdk/models/dream_types.py
edream_sdk/models/feed_types.py
edream_sdk/models/file_upload_types.py
edream_sdk/models/playlist_types.py
edream_sdk/models/user_types.py
edream_sdk/models/vote_types.py
edream_sdk/utils/api_utils.py
edream_sdk-0.1.0.dist-info/METADATA
edream_sdk-0.1.0.dist-info/WHEEL
edream_sdk-0.1.0.dist-info/top_level.txt
edream_sdk-0.1.0.dist-info/RECORD
