Metadata-Version: 2.1
Name: edream-sdk
Version: 0.1.0
Summary: edream sdk
Author-email: Scott Draves <spot@draves.org>, Alejandro Casillas <ealejandrocasillas@gmail.com>
Classifier: Programming Language :: Python :: 3
Classifier: Operating System :: OS Independent
Requires-Dist: requests
Requires-Dist: dacite
